INPLACE_TRUE_DIVIDE = 29
BINARY_XOR = 65
GET_YIELD_FROM_ITER = 69
LOAD_DEREF = 136
ROT_TWO = 2
BREAK_LOOP = 80
POP_TOP = 1
IMPORT_STAR = 84
LOAD_CLASSDEREF = 148
YIELD_FROM = 72
UNPACK_EX = 94
BUILD_SET_UNPACK = 153
SETUP_LOOP = 120
BUILD_MAP = 105
COMPARE_OP = 107
BINARY_SUBSCR = 25
BINARY_OR = 66
STORE_ATTR = 95
SETUP_ASYNC_WITH = 154
INPLACE_RSHIFT = 76
BINARY_POWER = 19
CALL_FUNCTION = 131
JUMP_FORWARD = 110
INPLACE_SUBTRACT = 56
BUILD_SLICE = 133
CALL_FUNCTION_VAR = 140
CALL_FUNCTION_VAR_KW = 142
SETUP_WITH = 143
STORE_SUBSCR = 60
INPLACE_AND = 77
NOP = 9
INPLACE_OR = 79
BINARY_SUBTRACT = 24
MAP_ADD = 147
INPLACE_ADD = 55
LOAD_NAME = 101
LOAD_CLOSURE = 135
STORE_NAME = 90
JUMP_IF_FALSE_OR_POP = 111
SET_ADD = 146
BINARY_ADD = 23
DELETE_GLOBAL = 98
UNARY_INVERT = 15
POP_JUMP_IF_TRUE = 115
GET_ANEXT = 51
LOAD_GLOBAL = 116
BUILD_MAP_UNPACK = 150
MAKE_FUNCTION = 132
BUILD_LIST_UNPACK = 149
DELETE_SUBSCR = 61
EXTENDED_ARG = 144
LIST_APPEND = 145
END_FINALLY = 88
BINARY_MATRIX_MULTIPLY = 16
IMPORT_FROM = 109
UNARY_NEGATIVE = 11
INPLACE_MATRIX_MULTIPLY = 17
CALL_FUNCTION_KW = 141
POP_JUMP_IF_FALSE = 114
BUILD_TUPLE = 102
FOR_ITER = 93
BUILD_LIST = 103
GET_AITER = 50
POP_BLOCK = 87
INPLACE_MODULO = 59
GET_AWAITABLE = 73
LOAD_BUILD_CLASS = 71
STORE_FAST = 125
INPLACE_FLOOR_DIVIDE = 28
BUILD_MAP_UNPACK_WITH_CALL = 151
PRINT_EXPR = 70
JUMP_ABSOLUTE = 113
INPLACE_LSHIFT = 75
BINARY_MULTIPLY = 20
BEFORE_ASYNC_WITH = 52
DUP_TOP = 4
BINARY_TRUE_DIVIDE = 27
BINARY_FLOOR_DIVIDE = 26
JUMP_IF_TRUE_OR_POP = 112
ROT_THREE = 3
INPLACE_XOR = 78
UNARY_POSITIVE = 10
BINARY_LSHIFT = 62
SETUP_EXCEPT = 121
DUP_TOP_TWO = 5
BINARY_MODULO = 22
STORE_GLOBAL = 97
CONTINUE_LOOP = 119
SETUP_FINALLY = 122
GET_ITER = 68
WITH_CLEANUP_START = 81
MAKE_CLOSURE = 134
BUILD_TUPLE_UNPACK = 152
INPLACE_POWER = 67
DELETE_ATTR = 96
DELETE_NAME = 91
WITH_CLEANUP_FINISH = 82
BUILD_SET = 104
UNARY_NOT = 12
RETURN_VALUE = 83
DELETE_FAST = 126
INPLACE_MULTIPLY = 57
LOAD_CONST = 100
POP_EXCEPT = 89
IMPORT_NAME = 108
BINARY_RSHIFT = 63
BINARY_AND = 64
LOAD_FAST = 124
YIELD_VALUE = 86
LOAD_ATTR = 106
DELETE_DEREF = 138
STORE_DEREF = 137
RAISE_VARARGS = 130
UNPACK_SEQUENCE = 92
